{"cameraMode":{"drawMode":0,"name":"Shaded","section":"Shading Mode"},"sceneLighting":false,"audioPlay":false,"sceneViewState":{"m_AlwaysRefresh":false,"showFog":true,"showSkybox":false,"showFlares":true,"showImageEffects":true,"showParticleSystems":true,"showVisualEffectGraphs":true,"m_FxEnabled":true},"in2DMode":false,"pivot":{"x":0.0,"y":243.0863494873047,"z":-1093.9444580078125},"rotation":{"x":0.25743749737739565,"y":-0.014493316411972046,"z":0.0038647260516881944,"w":0.9661850333213806},"size":367.521240234375,"orthographic":false}